TextExtract_Img_Aud/TextExtract_Img_Aud.py
TextExtract_Img_Aud/__init__.py
TextExtract_Img_Aud-0.1.dist-info/LICENSE.txt
TextExtract_Img_Aud-0.1.dist-info/METADATA
TextExtract_Img_Aud-0.1.dist-info/WHEEL
TextExtract_Img_Aud-0.1.dist-info/top_level.txt
TextExtract_Img_Aud-0.1.dist-info/RECORD
